AUTHORS.rst
LICENSE.txt
README.rst
pyproject.toml
setup.py
bit_lts/__init__.py
bit_lts/base32.py
bit_lts/base58.py
bit_lts/cli.py
bit_lts/constants.py
bit_lts/crypto.py
bit_lts/curve.py
bit_lts/exceptions.py
bit_lts/format.py
bit_lts/keygen.py
bit_lts/transaction.py
bit_lts/utils.py
bit_lts/wallet.py
bit_lts.egg-info/PKG-INFO
bit_lts.egg-info/SOURCES.txt
bit_lts.egg-info/dependency_links.txt
bit_lts.egg-info/entry_points.txt
bit_lts.egg-info/requires.txt
bit_lts.egg-info/top_level.txt
bit_lts/network/__init__.py
bit_lts/network/fees.py
bit_lts/network/meta.py
bit_lts/network/rates.py
bit_lts/network/services.py
tests/__init__.py
tests/samples.py
tests/test_base58.py
tests/test_curve.py
tests/test_format.py
tests/test_segwit_addr.py
tests/test_transaction.py
tests/test_utils.py
tests/test_wallet.py
tests/utils.py
tests/network/__init__.py
tests/network/test_fees.py
tests/network/test_meta.py
tests/network/test_rates.py
tests/network/test_services.py