Metadata-Version: 2.1
Name: bit-lts
Version: 0.8.0
Summary: Bitcoin made easy.
Author: Lts
Author-email: nail.velichko2016@yandex.ru
License: MIT
Keywords: bitcoin,cryptocurrency,payments,tools,wallet
Classifier: Development Status :: 4 - Beta
Classifier: Intended Audience :: Developers
Classifier: Intended Audience :: End Users/Desktop
Classifier: License :: OSI Approved :: MIT License
Classifier: Natural Language :: English
Classifier: Operating System :: OS Independent
Classifier: Programming Language :: Python :: 3.5
Classifier: Programming Language :: Python :: 3.6
Classifier: Programming Language :: Python :: 3.7
Classifier: Programming Language :: Python :: 3.10
Classifier: Programming Language :: Python :: Implementation :: CPython
Classifier: Programming Language :: Python :: Implementation :: PyPy
Provides-Extra: cli
Provides-Extra: cache
License-File: LICENSE.txt
License-File: AUTHORS.rst
